osgeo/gdal304.dll
osgeo/gdal_contour.exe
osgeo/gdal_create.exe
osgeo/gdal_grid.exe
osgeo/gdal_rasterize.exe
osgeo/gdal_translate.exe
osgeo/gdal_viewshed.exe
osgeo/gdaladdo.exe
osgeo/gdalbuildvrt.exe
osgeo/gdaldem.exe
osgeo/gdalenhance.exe
osgeo/gdalinfo.exe
osgeo/gdallocationinfo.exe
osgeo/gdalmanage.exe
osgeo/gdalmdiminfo.exe
osgeo/gdalmdimtranslate.exe
osgeo/gdalsrsinfo.exe
osgeo/gdaltindex.exe
osgeo/gdaltransform.exe
osgeo/gdalwarp.exe
osgeo/geos-license.txt
osgeo/geos_c.dll
osgeo/gnmanalyse.exe
osgeo/gnmmanage.exe
osgeo/nearblack.exe
osgeo/ogr2ogr.exe
osgeo/ogrinfo.exe
osgeo/ogrlineref.exe
osgeo/ogrtindex.exe
osgeo/setenv.cmd
osgeo/data/gdal/GDALLogoBW.svg
osgeo/data/gdal/GDALLogoColor.svg
osgeo/data/gdal/GDALLogoGS.svg
osgeo/data/gdal/bag_template.xml
osgeo/data/gdal/cubewerx_extra.wkt
osgeo/data/gdal/default.rsc
osgeo/data/gdal/ecw_cs.wkt
osgeo/data/gdal/eedaconf.json
osgeo/data/gdal/epsg.wkt
osgeo/data/gdal/esri_StatePlane_extra.wkt
osgeo/data/gdal/gdalicon.png
osgeo/data/gdal/gdalmdiminfo_output.schema.json
osgeo/data/gdal/gdalvrt.xsd
osgeo/data/gdal/gml_registry.xml
osgeo/data/gdal/gmlasconf.xml
osgeo/data/gdal/gmlasconf.xsd
osgeo/data/gdal/gt_datum.csv
osgeo/data/gdal/gt_ellips.csv
osgeo/data/gdal/header.dxf
osgeo/data/gdal/inspire_cp_BasicPropertyUnit.gfs
osgeo/data/gdal/inspire_cp_CadastralBoundary.gfs
osgeo/data/gdal/inspire_cp_CadastralParcel.gfs
osgeo/data/gdal/inspire_cp_CadastralZoning.gfs
osgeo/data/gdal/jpfgdgml_AdmArea.gfs
osgeo/data/gdal/jpfgdgml_AdmBdry.gfs
osgeo/data/gdal/jpfgdgml_AdmPt.gfs
osgeo/data/gdal/jpfgdgml_BldA.gfs
osgeo/data/gdal/jpfgdgml_BldL.gfs
osgeo/data/gdal/jpfgdgml_Cntr.gfs
osgeo/data/gdal/jpfgdgml_CommBdry.gfs
osgeo/data/gdal/jpfgdgml_CommPt.gfs
osgeo/data/gdal/jpfgdgml_Cstline.gfs
osgeo/data/gdal/jpfgdgml_ElevPt.gfs
osgeo/data/gdal/jpfgdgml_GCP.gfs
osgeo/data/gdal/jpfgdgml_LeveeEdge.gfs
osgeo/data/gdal/jpfgdgml_RailCL.gfs
osgeo/data/gdal/jpfgdgml_RdASL.gfs
osgeo/data/gdal/jpfgdgml_RdArea.gfs
geoai_GDAL-3.4.3.dist-info/METADATA
geoai_GDAL-3.4.3.dist-info/WHEEL
geoai_GDAL-3.4.3.dist-info/top_level.txt
geoai_GDAL-3.4.3.dist-info/RECORD
